README.md
setup.py
Zuba/__init__.py
Zuba/DataPreprocessing/__init__.py
Zuba/DataPreprocessing/createLoader.py
Zuba/DataPreprocessing/process.py
Zuba/Model_training/__init__.py
Zuba/Model_training/train.py
Zuba/Prediction/Classification.py
Zuba/Prediction/__init__.py
Zuba/Prediction/model_loader.py
Zuba/notebooks/__init__.py
Zuba_classify.egg-info/PKG-INFO
Zuba_classify.egg-info/SOURCES.txt
Zuba_classify.egg-info/dependency_links.txt
Zuba_classify.egg-info/requires.txt
Zuba_classify.egg-info/top_level.txt