Metadata-Version: 2.1
Name: Zuba_classify
Version: 0.0.1
Summary: A lightweight Nigerian language classifier.
Author: Ibrahim Olayiwola
Requires-Python: >=3.12
Requires-Dist: torch
Requires-Dist: tiktoken
Requires-Dist: huggingface_hub
Requires-Dist: transformers
Requires-Dist: requests
